foremast/__init__.py
foremast/__main__.py
foremast/args.py
foremast/consts.py
foremast/destroyer.py
foremast/exceptions.py
foremast/runner.py
foremast/validate.py
foremast/version.py
foremast/app/__init__.py
foremast/app/__main__.py
foremast/app/spinnaker_app.py
foremast/autoscaling_policy/__init__.py
foremast/autoscaling_policy/__main__.py
foremast/autoscaling_policy/create_policy.py
foremast/awslambda/__init__.py
foremast/awslambda/__main__.py
foremast/awslambda/awslambda.py
foremast/awslambda/awslambdaevent.py
foremast/awslambda/api_gateway_event/__init__.py
foremast/awslambda/api_gateway_event/__main__.py
foremast/awslambda/api_gateway_event/api_gateway_event.py
foremast/awslambda/cloudwatch_event/__init__.py
foremast/awslambda/cloudwatch_event/__main__.py
foremast/awslambda/cloudwatch_event/cloudwatch_event.py
foremast/awslambda/cloudwatch_event/destroy_cloudwatch_event/__init__.py
foremast/awslambda/cloudwatch_event/destroy_cloudwatch_event/__main__.py
foremast/awslambda/cloudwatch_event/destroy_cloudwatch_event/destroy_cloudwatch_event.py
foremast/awslambda/cloudwatch_log_event/__init__.py
foremast/awslambda/cloudwatch_log_event/__main__.py
foremast/awslambda/cloudwatch_log_event/cloudwatch_log_event.py
foremast/awslambda/cloudwatch_log_event/destroy_cloudwatch_log_event/__init__.py
foremast/awslambda/cloudwatch_log_event/destroy_cloudwatch_log_event/__main__.py
foremast/awslambda/cloudwatch_log_event/destroy_cloudwatch_log_event/destroy_cloudwatch_log_event.py
foremast/awslambda/event_source_mapping/__init__.py
foremast/awslambda/event_source_mapping/__main__.py
foremast/awslambda/event_source_mapping/event_source_mapping.py
foremast/awslambda/s3_event/__init__.py
foremast/awslambda/s3_event/__main__.py
foremast/awslambda/s3_event/s3_event.py
foremast/awslambda/s3_event/destroy_s3_event/__init__.py
foremast/awslambda/s3_event/destroy_s3_event/__main__.py
foremast/awslambda/s3_event/destroy_s3_event/destroy_s3_event.py
foremast-5.15.4.dist-info/LICENSE
foremast-5.15.4.dist-info/METADATA
foremast-5.15.4.dist-info/WHEEL
foremast-5.15.4.dist-info/entry_points.txt
foremast-5.15.4.dist-info/top_level.txt
foremast-5.15.4.dist-info/RECORD
