Metadata-Version: 2.1
Name: foremast
Version: 5.15.4
Summary: Tools for creating infrastructure and Spinnaker Pipelines.
Home-page: https://github.com/foremast/foremast
Download-URL: https://github.com/foremast/foremast
Author: Foremast
Author-email: joelvasallo+foremast@gmail.com
License: Apache License (2.0)
Keywords: aws gcp redbox gogo infrastructure netflixoss python spinnaker foremast
Platform: OS Independent
Classifier: Development Status :: 5 - Production/Stable
Classifier: Intended Audience :: Developers
Classifier: Programming Language :: Python :: 3.6
Classifier: Programming Language :: Python :: 3.7
Classifier: Programming Language :: Python :: 3.8
Classifier: Programming Language :: Python :: 3.9
Classifier: License :: OSI Approved :: Apache Software License
Classifier: Operating System :: OS Independent
License-File: LICENSE
Requires-Dist: awscli
Requires-Dist: boto3
Requires-Dist: deepmerge
Requires-Dist: foremast-utils
Requires-Dist: jinja2
Requires-Dist: pluginbase
Requires-Dist: python-gitlab
Requires-Dist: requests
Requires-Dist: slacker
Requires-Dist: tryagain
Requires-Dist: requests-toolbelt (==0.9.1)
Requires-Dist: PyJWT (==2.4.0)
Requires-Dist: cryptography (>=3.3.2)
Requires-Dist: google-cloud-secret-manager (==0.2.0)
Requires-Dist: google-api-python-client (==1.7.11)
Requires-Dist: google-auth (==1.11.2)
Requires-Dist: google-auth-httplib2 (==0.0.3)
Requires-Dist: tabulate (==0.8.7)
